{
  "bounds": {
    "center": [
      -0.007247488,
      0.779206127,
      -0.076893035
    ],
    "diagonal": 0.009324138,
    "dimensions": [
      0.003355578,
      0.004333436,
      0.007543273
    ],
    "max": [
      -0.005569699,
      0.781372845,
      -0.073121399
    ],
    "min": [
      -0.008925277,
      0.777039409,
      -0.080664672
    ]
  },
  "centroids": {
    "surface_area_weighted": [
      -0.007025516,
      0.779285607,
      -0.077032027
    ],
    "vertex_mean": [
      -0.006931932,
      0.779305014,
      -0.07708695
    ],
    "volume_if_watertight": [
      -0.00705028,
      0.77928048,
      -0.077079438
    ]
  },
  "cleaning": {
    "degenerate_faces_removed": 0,
    "unused_vertices_removed": 0,
    "vertices_welded": 0,
    "weld_tolerance": 0.0
  },
  "counts": {
    "analyzed_face_count": 98,
    "analyzed_vertex_count": 51,
    "source_face_count": 98,
    "source_vertex_count": 51
  },
  "mesh_name": "Allen_pineal_body_L",
  "pca": {
    "basis": "exact_uniform_surface_moments",
    "eigenvalues": [
      3.823e-06,
      1.206e-06,
      9.97e-07
    ],
    "oriented_bounds": {
      "center": [
        0.000114636,
        -3.3594e-05,
        0.000105736
      ],
      "dimensions": [
        0.007631009,
        0.003787005,
        0.003549235
      ],
      "max": [
        0.003930141,
        0.001859908,
        0.001880353
      ],
      "min": [
        -0.003700868,
        -0.001927097,
        -0.001668882
      ]
    },
    "principal_axes_world": [
      [
        -0.048903945,
        0.268826916,
        0.961946201
      ],
      [
        -0.20461222,
        0.939976593,
        -0.273089445
      ],
      [
        -0.977620705,
        -0.210181099,
        0.009036708
      ]
    ]
  },
  "sampling": {
    "cross_sections_pca": {
      "pca_axis_0": {
        "axis": 0,
        "in_plane_axes": [
          1,
          2
        ],
        "slices": [
          {
            "boundary_samples_normalized": [
              [
                -0.1350466,
                -0.0468779
              ],
              [
                -0.1265779,
                -0.0650316
              ],
              [
                -0.0662565,
                -0.1430876
              ],
              [
                -0.0637845,
                -0.1445572
              ],
              [
                -0.0297103,
                -0.1557221
              ],
              [
                0.0147145,
                -0.1586921
              ],
              [
                0.1116761,
                -0.1099011
              ],
              [
                0.1275442,
                -0.1013945
              ],
              [
                0.1283971,
                -0.1002033
              ],
              [
                0.1325688,
                -0.0911385
              ],
              [
                0.1545261,
                -0.027111
              ],
              [
                0.1507681,
                -0.0099965
              ],
              [
                0.092239,
                0.0777616
              ],
              [
                0.0492707,
                0.1175337
              ],
              [
                0.0285638,
                0.119934
              ],
              [
                -0.0808873,
                0.097091
              ],
              [
                -0.1408017,
                0.0273255
              ],
              [
                -0.1433093,
                0.0166378
              ]
            ],
            "bounds_normalized": {
              "dimensions": [
                0.297835405,
                0.27862608
              ],
              "max": [
                0.154526127,
                0.119933972
              ],
              "min": [
                -0.143309278,
                -0.158692108
              ]
            },
            "centroid_normalized": [
              0.011327453,
              -0.038746107
            ],
            "fraction": 0.1,
            "mask": {
              "encoding": "rows_top_to_bottom_1bit_text",
              "occupied_bbox_pixels": [
                11,
                11,
                20,
                19
              ],
              "occupied_fraction": 0.059570312,
              "occupied_pixel_count": 61,
              "origin": "bottom_left",
              "resolution": [
                32,
                32
              ],
              "rows": [
                "00000000000000000000000000000000",
                "00000000000000000000000000000000",
                "00000000000000000000000000000000",
                "00000000000000000000000000000000",
                "00000000000000000000000000000000",
                "00000000000000000000000000000000",
                "00000000000000000000000000000000",
                "00000000000000000000000000000000",
                "00000000000000000000000000000000",
                "00000000000000000000000000000000",
                "00000000000000000000000000000000",
                "00000000000000000000000000000000",
                "00000000000000011100000000000000",
                "00000000000001111110000000000000",
                "00000000000011111101000000000000",
                "00000000000111111111000000000000",
                "00000000000011111111100000000000",
                "00000000000011111111100000000000",
                "00000000000011111111000000000000",
                "00000000000001111111000000000000",
                "00000000000000111000000000000000",
                "00000000000000000000000000000000",
                "00000000000000000000000000000000",
                "00000000000000000000000000000000",
                "00000000000000000000000000000000",
                "00000000000000000000000000000000",
                "00000000000000000000000000000000",
                "00000000000000000000000000000000",
                "00000000000000000000000000000000",
                "00000000000000000000000000000000",
                "00000000000000000000000000000000",
                "00000000000000000000000000000000"
              ]
            },
            "plane_coordinate_native": -0.002937767,
            "segment_count": 18
          },
          {
            "boundary_samples_normalized": [
              [
                -0.247179,
                -0.0407447
              ],
              [
                -0.2481134,
                -0.0451386
              ],
              [
                -0.2478953,
                -0.0481143
              ],
              [
                -0.2224077,
                -0.1027501
              ],
              [
                -0.2118363,
                -0.1164295
              ],
              [
                -0.1620893,
                -0.1460046
              ],
              [
                -0.1482629,
                -0.150535
              ],
              [
                -0.0470006,
                -0.1723238
              ],
              [
                0.0221722,
                -0.1874869
              ],
              [
                0.0657459,
                -0.1974154
              ],
              [
                0.1309473,
                -0.1958338
              ],
              [
                0.1436641,
                -0.1961535
              ],
              [
                0.1896746,
                -0.1318096
              ],
              [
                0.1996185,
                -0.1146188
              ],
              [
                0.1908619,
                -0.0793644
              ],
              [
                0.1877856,
                0.0321379
              ],
              [
                0.1508925,
                0.1037424
              ],
              [
                0.1330125,
                0.1288233
              ],
              [
                0.1026131,
                0.1564337
              ],
              [
                0.0589319,
                0.187698
              ],
              [
                0.0020981,
                0.1740416
              ],
              [
                -0.075246,
                0.1505222
              ],
              [
                -0.1997744,
                0.0659483
              ],
              [
                -0.2121983,
                0.0516875
              ]
            ],
            "bounds_normalized": {
              "dimensions": [
                0.447731927,
                0.385113363
              ],
              "max": [
                0.19961851,
                0.187697993
              ],
              "min": [
                -0.248113417,
                -0.197415371
              ]
            },
            "centroid_normalized": [
              -0.018499378,
              -0.036403679
            ],
            "fraction": 0.25,
            "mask": {
              "encoding": "rows_top_to_bottom_1bit_text",
              "occupied_bbox_pixels": [
                9,
                10,
                21,
                21
              ],
              "occupied_fraction": 0.119140625,
              "occupied_pixel_count": 122,
              "origin": "bottom_left",
              "resolution": [
                32,
                32
              ],
              "rows": [
                "00000000000000000000000000000000",
                "00000000000000000000000000000000",
                "00000000000000000000000000000000",
                "00000000000000000000000000000000",
                "00000000000000000000000000000000",
                "00000000000000000000000000000000",
                "00000000000000000000000000000000",
                "00000000000000000000000000000000",
                "00000000000000000000000000000000",
                "00000000000000000000000000000000",
                "00000000000000001100000000000000",
                "00000000000001111111000000000000",
                "00000000000011111111100000000000",
                "00000000001111111111100000000000",
                "00000000001111111111110000000000",
                "00000000011111111111110000000000",
                "00000000011111111111110000000000",
                "00000000011111111111110000000000",
                "00000000011111111111110000000000",
                "00000000011111111111110000000000",
                "00000000000111111111100000000000",
                "00000000000000011111100000000000",
                "00000000000000000000000000000000",
                "00000000000000000000000000000000",
                "00000000000000000000000000000000",
                "00000000000000000000000000000000",
                "00000000000000000000000000000000",
                "00000000000000000000000000000000",
                "00000000000000000000000000000000",
                "00000000000000000000000000000000",
                "00000000000000000000000000000000",
                "00000000000000000000000000000000"
              ]
            },
            "plane_coordinate_native": -0.001793116,
            "segment_count": 24
          },
          {
            "boundary_samples_normalized": [
              [
                -0.2439417,
                -0.0282106
              ],
              [
                -0.2448619,
                -0.0325377
              ],
              [
                -0.2446518,
                -0.0354045
              ],
              [
                -0.2374481,
                -0.13019
              ],
              [
                -0.1836125,
                -0.1628009
              ],
              [
                -0.1732261,
                -0.1687527
              ],
              [
                -0.1534363,
                -0.1730109
              ],
              [
                0.0404336,
                -0.2155086
              ],
              [
                0.0812648,
                -0.2248122
              ],
              [
                0.132106,
                -0.2186433
              ],
              [
                0.1754599,
                -0.1877822
              ],
              [
                0.2170354,
                -0.162644
              ],
              [
                0.2366298,
                -0.1219194
              ],
              [
                0.2475566,
                -0.0528512
              ],
              [
                0.2354834,
                0.0121186
              ],
              [
                0.2130044,
                0.0917546
              ],
              [
                0.1921836,
                0.1267026
              ],
              [
                0.1596226,
                0.1841414
              ],
              [
                0.139792,
                0.1922357
              ],
              [
                0.0702596,
                0.2206822
              ],
              [
                0.0263506,
                0.2229586
              ],
              [
                -0.0553995,
                0.2219121
              ],
              [
                -0.0698775,
                0.2126645
              ],
              [
                -0.0821029,
                0.1977426
              ],
              [
                -0.2134967,
                0.0498963
              ]
            ],
            "bounds_normalized": {
              "dimensions": [
                0.492418532,
                0.447770725
              ],
              "max": [
                0.247556593,
                0.222958563
              ],
              "min": [
                -0.244861939,
                -0.224812162
              ]
            },
            "centroid_normalized": [
              0.010605084,
              -0.007290357
            ],
            "fraction": 0.5,
            "mask": {
              "encoding": "rows_top_to_bottom_1bit_text",
              "occupied_bbox_pixels": [
                9,
                9,
                22,
                22
              ],
              "occupied_fraction": 0.15234375,
              "occupied_pixel_count": 156,
              "origin": "bottom_left",
              "resolution": [
                32,
                32
              ],
              "rows": [
                "00000000000000000000000000000000",
                "00000000000000000000000000000000",
                "00000000000000000000000000000000",
                "00000000000000000000000000000000",
                "00000000000000000000000000000000",
                "00000000000000000000000000000000",
                "00000000000000000000000000000000",
                "00000000000000000000000000000000",
                "00000000000000000000000000000000",
                "00000000000000111100000000000000",
                "00000000000001111111100000000000",
                "00000000000011111111110000000000",
                "00000000000111111111110000000000",
                "00000000001111111111101000000000",
                "00000000011111111111111000000000",
                "00000000011111111111111000000000",
                "00000000011111111111111000000000",
                "00000000011111111111111000000000",
                "00000000011111111111111000000000",
                "00000000011111111111111000000000",
                "00000000011111111111111000000000",
                "00000000000011111111100000000000",
                "00000000000000001111000000000000",
                "00000000000000000000000000000000",
                "00000000000000000000000000000000",
                "00000000000000000000000000000000",
                "00000000000000000000000000000000",
                "00000000000000000000000000000000",
                "00000000000000000000000000000000",
                "00000000000000000000000000000000",
                "00000000000000000000000000000000",
                "00000000000000000000000000000000"
              ]
            },
            "plane_coordinate_native": 0.000114636,
            "segment_count": 25
          },
          {
            "boundary_samples_normalized": [
              [
                -0.1926868,
                -0.0150576
              ],
              [
                -0.2006674,
                -0.0321989
              ],
              [
                -0.1582611,
                -0.1035677
              ],
              [
                -0.1378042,
                -0.1321251
              ],
              [
                -0.0928097,
                -0.1402645
              ],
              [
                0.0477109,
                -0.1753009
              ],
              [
                0.1459095,
                -0.1357704
              ],
              [
                0.1740191,
                -0.1169273
              ],
              [
                0.1739517,
                -0.1026418
              ],
              [
                0.2061542,
                -0.0502832
              ],
              [
                0.2019799,
                -0.0191056
              ],
              [
                0.1878216,
                0.0447473
              ],
              [
                0.1706234,
                0.0796573
              ],
              [
                0.1205627,
                0.1270349
              ],
              [
                0.0635415,
                0.1715159
              ],
              [
                0.0394485,
                0.1667809
              ],
              [
                -0.0445094,
                0.1489695
              ],
              [
                -0.0998238,
                0.1122926
              ],
              [
                -0.1798081,
                0.0352747
              ]
            ],
            "bounds_normalized": {
              "dimensions": [
                0.406821548,
                0.346816791
              ],
              "max": [
                0.206154193,
                0.171515895
              ],
              "min": [
                -0.200667356,
                -0.175300896
              ]
            },
            "centroid_normalized": [
              0.022386981,
              -0.007208966
            ],
            "fraction": 0.75,
            "mask": {
              "encoding": "rows_top_to_bottom_1bit_text",
              "occupied_bbox_pixels": [
                10,
                11,
                21,
                20
              ],
              "occupied_fraction": 0.09375,
              "occupied_pixel_count": 96,
              "origin": "bottom_left",
              "resolution": [
                32,
                32
              ],
              "rows": [
                "00000000000000000000000000000000",
                "00000000000000000000000000000000",
                "00000000000000000000000000000000",
                "00000000000000000000000000000000",
                "00000000000000000000000000000000",
                "00000000000000000000000000000000",
                "00000000000000000000000000000000",
                "00000000000000000000000000000000",
                "00000000000000000000000000000000",
                "00000000000000000000000000000000",
                "00000000000000000000000000000000",
                "00000000000000111110000000000000",
                "00000000000001111111000000000000",
                "00000000000011111111100000000000",
                "00000000000111111111010000000000",
                "00000000001111111111110000000000",
                "00000000001111111111110000000000",
                "00000000001111111111110000000000",
                "00000000001111111111110000000000",
                "00000000000111111111100000000000",
                "00000000000001111111000000000000",
                "00000000000000000000000000000000",
                "00000000000000000000000000000000",
                "00000000000000000000000000000000",
                "00000000000000000000000000000000",
                "00000000000000000000000000000000",
                "00000000000000000000000000000000",
                "00000000000000000000000000000000",
                "00000000000000000000000000000000",
                "00000000000000000000000000000000",
                "00000000000000000000000000000000",
                "00000000000000000000000000000000"
              ]
            },
            "plane_coordinate_native": 0.002022389,
            "segment_count": 19
          },
          {
            "boundary_samples_normalized": [
              [
                -0.1473459,
                -0.059747
              ],
              [
                -0.1329865,
                -0.0839136
              ],
              [
                -0.0988131,
                -0.1377897
              ],
              [
                -0.0605241,
                -0.152177
              ],
              [
                -0.0174516,
                -0.1400804
              ],
              [
                0.0838554,
                -0.0875961
              ],
              [
                0.1053942,
                -0.05805
              ],
              [
                0.0991396,
                -0.013253
              ],
              [
                0.0781768,
                0.0521741
              ],
              [
                0.0605294,
                0.0688757
              ],
              [
                0.0521109,
                0.0754428
              ],
              [
                -0.0457546,
                0.0562094
              ],
              [
                -0.072856,
                0.0504599
              ],
              [
                -0.0907113,
                0.0386207
              ],
              [
                -0.11653,
                0.0137596
              ],
              [
                -0.1206871,
                -0.0024875
              ]
            ],
            "bounds_normalized": {
              "dimensions": [
                0.252740119,
                0.22761982
              ],
              "max": [
                0.10539422,
                0.07544278
              ],
              "min": [
                -0.147345899,
                -0.152177039
              ]
            },
            "centroid_normalized": [
              -0.026528364,
              -0.023722028
            ],
            "fraction": 0.9,
            "mask": {
              "encoding": "rows_top_to_bottom_1bit_text",
              "occupied_bbox_pixels": [
                11,
                11,
                18,
                18
              ],
              "occupied_fraction": 0.043945312,
              "occupied_pixel_count": 45,
              "origin": "bottom_left",
              "resolution": [
                32,
                32
              ],
              "rows": [
                "00000000000000000000000000000000",
                "00000000000000000000000000000000",
                "00000000000000000000000000000000",
                "00000000000000000000000000000000",
                "00000000000000000000000000000000",
                "00000000000000000000000000000000",
                "00000000000000000000000000000000",
                "00000000000000000000000000000000",
                "00000000000000000000000000000000",
                "00000000000000000000000000000000",
                "00000000000000000000000000000000",
                "00000000000000000000000000000000",
                "00000000000000000000000000000000",
                "00000000000000001100000000000000",
                "00000000000001111110000000000000",
                "00000000000011111110000000000000",
                "00000000000011111110000000000000",
                "00000000000111111110000000000000",
                "00000000000011111110000000000000",
                "00000000000011111100000000000000",
                "00000000000001100000000000000000",
                "00000000000000000000000000000000",
                "00000000000000000000000000000000",
                "00000000000000000000000000000000",
                "00000000000000000000000000000000",
                "00000000000000000000000000000000",
                "00000000000000000000000000000000",
                "00000000000000000000000000000000",
                "00000000000000000000000000000000",
                "00000000000000000000000000000000",
                "00000000000000000000000000000000",
                "00000000000000000000000000000000"
              ]
            },
            "plane_coordinate_native": 0.00316704,
            "segment_count": 16
          }
        ]
      },
      "pca_axis_1": {
        "axis": 1,
        "in_plane_axes": [
          0,
          2
        ],
        "slices": [
          {
            "boundary_samples_normalized": [
              [
                -0.3166541,
                -0.0459436
              ],
              [
                -0.2874126,
                -0.0933425
              ],
              [
                -0.2637349,
                -0.1188705
              ],
              [
                -0.2211337,
                -0.1358799
              ],
              [
                -0.0549152,
                -0.1497004
              ],
              [
                0.0272361,
                -0.1558021
              ],
              [
                0.116943,
                -0.0942741
              ],
              [
                0.172678,
                -0.0568729
              ],
              [
                0.2104331,
                -0.0522409
              ],
              [
                0.2560799,
                -0.0333155
              ],
              [
                0.2378763,
                -0.0160736
              ],
              [
                0.2056766,
                0.0416321
              ],
              [
                0.1956338,
                0.0471521
              ],
              [
                0.1916667,
                0.0473247
              ],
              [
                -0.1865445,
                0.0856836
              ],
              [
                -0.2515625,
                0.0663449
              ],
              [
                -0.2818699,
                0.0458004
              ],
              [
                -0.3230534,
                -0.0085606
              ]
            ],
            "bounds_normalized": {
              "dimensions": [
                0.579133345,
                0.241485635
              ],
              "max": [
                0.256079911,
                0.08568358
              ],
              "min": [
                -0.323053434,
                -0.155802055
              ]
            },
            "centroid_normalized": [
              -0.031814305,
              -0.034829932
            ],
            "fraction": 0.1,
            "mask": {
              "encoding": "rows_top_to_bottom_1bit_text",
              "occupied_bbox_pixels": [
                6,
                11,
                23,
                18
              ],
              "occupied_fraction": 0.095703125,
              "occupied_pixel_count": 98,
              "origin": "bottom_left",
              "resolution": [
                32,
                32
              ],
              "rows": [
                "00000000000000000000000000000000",
                "00000000000000000000000000000000",
                "00000000000000000000000000000000",
                "00000000000000000000000000000000",
                "00000000000000000000000000000000",
                "00000000000000000000000000000000",
                "00000000000000000000000000000000",
                "00000000000000000000000000000000",
                "00000000000000000000000000000000",
                "00000000000000000000000000000000",
                "00000000000000000000000000000000",
                "00000000000000000000000000000000",
                "00000000000000000000000000000000",
                "00000000011111100000000000000000",
                "00000000111111011111110000000000",
                "00000001111111111111101000000000",
                "00000011111111111111111100000000",
                "00000001111111111111111000000000",
                "00000001111111111111000000000000",
                "00000000111111111110000000000000",
                "00000000000111111000000000000000",
                "00000000000000000000000000000000",
                "00000000000000000000000000000000",
                "00000000000000000000000000000000",
                "00000000000000000000000000000000",
                "00000000000000000000000000000000",
                "00000000000000000000000000000000",
                "00000000000000000000000000000000",
                "00000000000000000000000000000000",
                "00000000000000000000000000000000",
                "00000000000000000000000000000000",
                "00000000000000000000000000000000"
              ]
            },
            "plane_coordinate_native": -0.001548396,
            "segment_count": 18
          },
          {
            "boundary_samples_normalized": [
              [
                -0.4039314,
                -0.0640431
              ],
              [
                -0.3404349,
                -0.1325017
              ],
              [
                -0.308018,
                -0.1454448
              ],
              [
                -0.2709327,
                -0.1537663
              ],
              [
                -0.0689854,
                -0.1728213
              ],
              [
                0.0421497,
                -0.1834985
              ],
              [
                0.1325297,
                -0.1457212
              ],
              [
                0.144097,
                -0.1405713
              ],
              [
                0.2651559,
                -0.1337572
              ],
              [
                0.2823264,
                -0.135214
              ],
              [
                0.3140555,
                -0.1333499
              ],
              [
                0.4413819,
                -0.0809447
              ],
              [
                0.4508482,
                -0.0695853
              ],
              [
                0.4485696,
                -0.0557492
              ],
              [
                0.3929601,
                -0.0030775
              ],
              [
                0.3821352,
                0.016322
              ],
              [
                0.1577382,
                0.1396602
              ],
              [
                0.069096,
                0.1435168
              ],
              [
                -0.1032948,
                0.161001
              ],
              [
                -0.3432721,
                0.0896233
              ],
              [
                -0.3910974,
                0.0572039
              ],
              [
                -0.4147372,
                0.0296109
              ],
              [
                -0.4218434,
                -0.0036814
              ],
              [
                -0.4144213,
                -0.0470396
              ]
            ],
            "bounds_normalized": {
              "dimensions": [
                0.872691653,
                0.344499532
              ],
              "max": [
                0.450848245,
                0.161001006
              ],
              "min": [
                -0.421843408,
                -0.183498526
              ]
            },
            "centroid_normalized": [
              0.001753109,
              -0.048492863
            ],
            "fraction": 0.25,
            "mask": {
              "encoding": "rows_top_to_bottom_1bit_text",
              "occupied_bbox_pixels": [
                4,
                10,
                28,
                20
              ],
              "occupied_fraction": 0.190429688,
              "occupied_pixel_count": 195,
              "origin": "bottom_left",
              "resolution": [
                32,
                32
              ],
              "rows": [
                "00000000000000000000000000000000",
                "00000000000000000000000000000000",
                "00000000000000000000000000000000",
                "00000000000000000000000000000000",
                "00000000000000000000000000000000",
                "00000000000000000000000000000000",
                "00000000000000000000000000000000",
                "00000000000000000000000000000000",
                "00000000000000000000000000000000",
                "00000000000000000000000000000000",
                "00000000000000000000000000000000",
                "00000000000111111110000000000000",
                "00000000111111111101110000000000",
                "00000111111111111111111100000000",
                "00001111111111111111111011000000",
                "00001111111111111111111110100000",
                "00001111111111111111111111110000",
                "00001111111111111111111111111000",
                "00001111111111111111111111111000",
                "00000111111111111111111111100000",
                "00000001111111111111000000000000",
                "00000000000000011100000000000000",
                "00000000000000000000000000000000",
                "00000000000000000000000000000000",
                "00000000000000000000000000000000",
                "00000000000000000000000000000000",
                "00000000000000000000000000000000",
                "00000000000000000000000000000000",
                "00000000000000000000000000000000",
                "00000000000000000000000000000000",
                "00000000000000000000000000000000",
                "00000000000000000000000000000000"
              ]
            },
            "plane_coordinate_native": -0.000980346,
            "segment_count": 24
          },
          {
            "boundary_samples_normalized": [
              [
                -0.4901966,
                -0.0435368
              ],
              [
                -0.4635768,
                -0.0822761
              ],
              [
                -0.3919459,
                -0.1672643
              ],
              [
                -0.3782637,
                -0.1703345
              ],
              [
                -0.3603966,
                -0.1720203
              ],
              [
                0.0391713,
                -0.2104086
              ],
              [
                0.0625215,
                -0.2006487
              ],
              [
                0.1474805,
                -0.1628243
              ],
              [
                0.2049979,
                -0.1595867
              ],
              [
                0.3234625,
                -0.169638
              ],
              [
                0.3553465,
                -0.1588444
              ],
              [
                0.4542562,
                -0.0972546
              ],
              [
                0.4901836,
                -0.0721416
              ],
              [
                0.4993465,
                -0.064459
              ],
              [
                0.4958514,
                -0.051737
              ],
              [
                0.4426986,
                0.038493
              ],
              [
                0.319449,
                0.115587
              ],
              [
                0.1673356,
                0.2093861
              ],
              [
                0.077003,
                0.2174504
              ],
              [
                -0.0798963,
                0.2279864
              ],
              [
                -0.2534652,
                0.1722917
              ],
              [
                -0.3857167,
                0.1247461
              ],
              [
                -0.4334843,
                0.0887163
              ],
              [
                -0.4743431,
                0.0465832
              ],
              [
                -0.4931019,
                -0.0034173
              ]
            ],
            "bounds_normalized": {
              "dimensions": [
                0.992448375,
                0.438395058
              ],
              "max": [
                0.499346486,
                0.22798641
              ],
              "min": [
                -0.49310189,
                -0.210408648
              ]
            },
            "centroid_normalized": [
              -0.00501132,
              -0.02980609
            ],
            "fraction": 0.5,
            "mask": {
              "encoding": "rows_top_to_bottom_1bit_text",
              "occupied_bbox_pixels": [
                2,
                10,
                30,
                22
              ],
              "occupied_fraction": 0.276367188,
              "occupied_pixel_count": 283,
              "origin": "bottom_left",
              "resolution": [
                32,
                32
              ],
              "rows": [
                "00000000000000000000000000000000",
                "00000000000000000000000000000000",
                "00000000000000000000000000000000",
                "00000000000000000000000000000000",
                "00000000000000000000000000000000",
                "00000000000000000000000000000000",
                "00000000000000000000000000000000",
                "00000000000000000000000000000000",
                "00000000000000000000000000000000",
                "00000000000011111111000000000000",
                "00000000011111111110110000000000",
                "00000011111111111111111100000000",
                "00001111111111111111111011000000",
                "00011111111111111111111111100000",
                "00111111111111111111111111111000",
                "00111111111111111111111111111000",
                "00111111111111111111111111111100",
                "00111111111111111111111111111110",
                "00111111111111111111111111111100",
                "00011111111111111111111111111000",
                "00001111111111111111111111100000",
                "00000001111111111110000000000000",
                "00000000000000000000000000000000",
                "00000000000000000000000000000000",
                "00000000000000000000000000000000",
                "00000000000000000000000000000000",
                "00000000000000000000000000000000",
                "00000000000000000000000000000000",
                "00000000000000000000000000000000",
                "00000000000000000000000000000000",
                "00000000000000000000000000000000",
                "00000000000000000000000000000000"
              ]
            },
            "plane_coordinate_native": -3.3594e-05,
            "segment_count": 25
          },
          {
            "boundary_samples_normalized": [
              [
                -0.4262131,
                -0.0309151
              ],
              [
                -0.405597,
                -0.0977791
              ],
              [
                -0.4014075,
                -0.1021858
              ],
              [
                -0.2879724,
                -0.1886693
              ],
              [
                -0.0993967,
                -0.2250779
              ],
              [
                -0.0429006,
                -0.2304701
              ],
              [
                0.0611209,
                -0.2041588
              ],
              [
                0.1446311,
                -0.1765492
              ],
              [
                0.1853544,
                -0.1664479
              ],
              [
                0.3049113,
                -0.1259744
              ],
              [
                0.3418428,
                -0.1029776
              ],
              [
                0.379409,
                -0.0574121
              ],
              [
                0.3704751,
                0.000888
              ],
              [
                0.3574879,
                0.0413296
              ],
              [
                0.2412459,
                0.1304291
              ],
              [
                0.1661409,
                0.1829975
              ],
              [
                0.0435904,
                0.1945466
              ],
              [
                -0.0837716,
                0.2065922
              ],
              [
                -0.3211101,
                0.1071562
              ],
              [
                -0.3257956,
                0.1049017
              ],
              [
                -0.3295167,
                0.1024025
              ],
              [
                -0.4184943,
                0.0110526
              ]
            ],
            "bounds_normalized": {
              "dimensions": [
                0.805622091,
                0.437062275
              ],
              "max": [
                0.379408954,
                0.206592199
              ],
              "min": [
                -0.426213137,
                -0.230470076
              ]
            },
            "centroid_normalized": [
              -0.024816636,
              -0.028469161
            ],
            "fraction": 0.75,
            "mask": {
              "encoding": "rows_top_to_bottom_1bit_text",
              "occupied_bbox_pixels": [
                3,
                9,
                26,
                21
              ],
              "occupied_fraction": 0.225585938,
              "occupied_pixel_count": 231,
              "origin": "bottom_left",
              "resolution": [
                32,
                32
              ],
              "rows": [
                "00000000000000000000000000000000",
                "00000000000000000000000000000000",
                "00000000000000000000000000000000",
                "00000000000000000000000000000000",
                "00000000000000000000000000000000",
                "00000000000000000000000000000000",
                "00000000000000000000000000000000",
                "00000000000000000000000000000000",
                "00000000000000000000000000000000",
                "00000000000000000000000000000000",
                "00000000000111111111100000000000",
                "00000000011111111111011000000000",
                "00000011111111111111111100000000",
                "00000011111111111111111010000000",
                "00000111111111111111111101100000",
                "00001111111111111111111111100000",
                "00011111111111111111111111100000",
                "00001111111111111111111111100000",
                "00001111111111111111111111100000",
                "00001111111111111111111111000000",
                "00000011111111111111111000000000",
                "00000001111111111111000000000000",
                "00000000000111111000000000000000",
                "00000000000000000000000000000000",
                "00000000000000000000000000000000",
                "00000000000000000000000000000000",
                "00000000000000000000000000000000",
                "00000000000000000000000000000000",
                "00000000000000000000000000000000",
                "00000000000000000000000000000000",
                "00000000000000000000000000000000",
                "00000000000000000000000000000000"
              ]
            },
            "plane_coordinate_native": 0.000913157,
            "segment_count": 22
          },
          {
            "boundary_samples_normalized": [
              [
                -0.2527009,
                -0.1143112
              ],
              [
                -0.1247958,
                -0.2199516
              ],
              [
                -0.1223982,
                -0.221876
              ],
              [
                -0.1217102,
                -0.2220072
              ],
              [
                0.0379635,
                -0.1588257
              ],
              [
                0.1072149,
                -0.1359303
              ],
              [
                0.1813411,
                -0.1175434
              ],
              [
                0.1808295,
                -0.0788475
              ],
              [
                0.2880725,
                -0.0538408
              ],
              [
                0.2796114,
                -0.0403552
              ],
              [
                0.2015792,
                0.0569268
              ],
              [
                0.1233525,
                0.1116416
              ],
              [
                -0.0316896,
                0.1172331
              ],
              [
                -0.0780399,
                0.1196955
              ],
              [
                -0.1154713,
                0.1016846
              ],
              [
                -0.1675157,
                0.0667299
              ],
              [
                -0.1813164,
                -0.00407
              ]
            ],
            "bounds_normalized": {
              "dimensions": [
                0.540773402,
                0.341702727
              ],
              "max": [
                0.288072525,
                0.119695494
              ],
              "min": [
                -0.252700878,
                -0.222007233
              ]
            },
            "centroid_normalized": [
              0.01201923,
              -0.046685138
            ],
            "fraction": 0.9,
            "mask": {
              "encoding": "rows_top_to_bottom_1bit_text",
              "occupied_bbox_pixels": [
                8,
                9,
                24,
                19
              ],
              "occupied_fraction": 0.110351562,
              "occupied_pixel_count": 113,
              "origin": "bottom_left",
              "resolution": [
                32,
                32
              ],
              "rows": [
                "00000000000000000000000000000000",
                "00000000000000000000000000000000",
                "00000000000000000000000000000000",
                "00000000000000000000000000000000",
                "00000000000000000000000000000000",
                "00000000000000000000000000000000",
                "00000000000000000000000000000000",
                "00000000000000000000000000000000",
                "00000000000000000000000000000000",
                "00000000000000000000000000000000",
                "00000000000000000000000000000000",
                "00000000000000000000000000000000",
                "00000000000001111111000000000000",
                "00000000000111111110100000000000",
                "00000000000111111111111000000000",
                "00000000000111111111111000000000",
                "00000000001111111111110100000000",
                "00000000011111111111111110000000",
                "00000000011111111111110000000000",
                "00000000111111111111110000000000",
                "00000000011111111110000000000000",
                "00000000000111110000000000000000",
                "00000000000011000000000000000000",
                "00000000000000000000000000000000",
                "00000000000000000000000000000000",
                "00000000000000000000000000000000",
                "00000000000000000000000000000000",
                "00000000000000000000000000000000",
                "00000000000000000000000000000000",
                "00000000000000000000000000000000",
                "00000000000000000000000000000000",
                "00000000000000000000000000000000"
              ]
            },
            "plane_coordinate_native": 0.001481207,
            "segment_count": 17
          }
        ]
      },
      "pca_axis_2": {
        "axis": 2,
        "in_plane_axes": [
          0,
          1
        ],
        "slices": [
          {
            "boundary_samples_normalized": [
              [
                -0.3119159,
                0.0417692
              ],
              [
                -0.2628845,
                0.021231
              ],
              [
                0.0418681,
                -0.1123364
              ],
              [
                0.0811375,
                -0.0329908
              ],
              [
                0.1411535,
                0.1065332
              ],
              [
                0.1375664,
                0.1140109
              ],
              [
                0.0022805,
                0.1768443
              ],
              [
                -0.0480887,
                0.2098072
              ],
              [
                -0.1281527,
                0.2165167
              ],
              [
                -0.1729627,
                0.1951085
              ],
              [
                -0.2829937,
                0.1319576
              ],
              [
                -0.2877127,
                0.1293352
              ],
              [
                -0.3037865,
                0.1064754
              ]
            ],
            "bounds_normalized": {
              "dimensions": [
                0.45306943,
                0.328853045
              ],
              "max": [
                0.141153518,
                0.216516682
              ],
              "min": [
                -0.311915912,
                -0.112336362
              ]
            },
            "centroid_normalized": [
              -0.107268573,
              0.100327851
            ],
            "fraction": 0.1,
            "mask": {
              "encoding": "rows_top_to_bottom_1bit_text",
              "occupied_bbox_pixels": [
                7,
                12,
                19,
                22
              ],
              "occupied_fraction": 0.088867188,
              "occupied_pixel_count": 91,
              "origin": "bottom_left",
              "resolution": [
                32,
                32
              ],
              "rows": [
                "00000000000000000000000000000000",
                "00000000000000000000000000000000",
                "00000000000000000000000000000000",
                "00000000000000000000000000000000",
                "00000000000000000000000000000000",
                "00000000000000000000000000000000",
                "00000000000000000000000000000000",
                "00000000000000000000000000000000",
                "00000000000000000000000000000000",
                "00000000000011000000000000000000",
                "00000000001110110000000000000000",
                "00000000111111111100000000000000",
                "00000001111111111111000000000000",
                "00000001111111111111000000000000",
                "00000001111111111111000000000000",
                "00000001111111111110000000000000",
                "00000000011111111110000000000000",
                "00000000000011111110000000000000",
                "00000000000000111100000000000000",
                "00000000000000001100000000000000",
                "00000000000000000000000000000000",
                "00000000000000000000000000000000",
                "00000000000000000000000000000000",
                "00000000000000000000000000000000",
                "00000000000000000000000000000000",
                "00000000000000000000000000000000",
                "00000000000000000000000000000000",
                "00000000000000000000000000000000",
                "00000000000000000000000000000000",
                "00000000000000000000000000000000",
                "00000000000000000000000000000000",
                "00000000000000000000000000000000"
              ]
            },
            "plane_coordinate_native": -0.001313958,
            "segment_count": 13
          },
          {
            "boundary_samples_normalized": [
              [
                -0.4331138,
                -0.032054
              ],
              [
                -0.4256905,
                -0.0655708
              ],
              [
                -0.2491402,
                -0.2126708
              ],
              [
                -0.2187864,
                -0.2330563
              ],
              [
                -0.1950219,
                -0.2365045
              ],
              [
                -0.1562339,
                -0.2412604
              ],
              [
                0.0046653,
                -0.2384232
              ],
              [
                0.0273836,
                -0.2355551
              ],
              [
                0.0963941,
                -0.1910739
              ],
              [
                0.1511108,
                -0.157848
              ],
              [
                0.2597971,
                -0.1482961
              ],
              [
                0.3117714,
                -0.1354921
              ],
              [
                0.4346018,
                -0.1034254
              ],
              [
                0.456287,
                -0.083676
              ],
              [
                0.4507753,
                -0.0590685
              ],
              [
                0.430157,
                -0.0077516
              ],
              [
                0.2915593,
                0.1588332
              ],
              [
                0.2905166,
                0.1597552
              ],
              [
                0.2896368,
                0.1598814
              ],
              [
                0.0898389,
                0.2311303
              ],
              [
                -0.1177838,
                0.245903
              ],
              [
                -0.1357569,
                0.2438522
              ],
              [
                -0.2354429,
                0.2056142
              ],
              [
                -0.2720642,
                0.1881182
              ],
              [
                -0.2793895,
                0.183914
              ],
              [
                -0.3802585,
                0.127859
              ],
              [
                -0.3988369,
                0.1014374
              ],
              [
                -0.4362311,
                0.023269
              ]
            ],
            "bounds_normalized": {
              "dimensions": [
                0.892518109,
                0.487163419
              ],
              "max": [
                0.456287023,
                0.245903019
              ],
              "min": [
                -0.436231086,
                -0.2412604
              ]
            },
            "centroid_normalized": [
              -0.012473407,
              -0.012577125
            ],
            "fraction": 0.25,
            "mask": {
              "encoding": "rows_top_to_bottom_1bit_text",
              "occupied_bbox_pixels": [
                3,
                9,
                28,
                22
              ],
              "occupied_fraction": 0.270507812,
              "occupied_pixel_count": 277,
              "origin": "bottom_left",
              "resolution": [
                32,
                32
              ],
              "rows": [
                "00000000000000000000000000000000",
                "00000000000000000000000000000000",
                "00000000000000000000000000000000",
                "00000000000000000000000000000000",
                "00000000000000000000000000000000",
                "00000000000000000000000000000000",
                "00000000000000000000000000000000",
                "00000000000000000000000000000000",
                "00000000000000000000000000000000",
                "00000000011111111111000000000000",
                "00000000111111111110111000000000",
                "00000011111111111111111110000000",
                "00000111111111111111111111000000",
                "00001111111111111111111111100000",
                "00011111111111111111111111100000",
                "00011111111111111111111111110000",
                "00011111111111111111111111101000",
                "00011111111111111111111111111000",
                "00001111111111111111111111111000",
                "00000111111111111111111111110000",
                "00000011111111111111111100000000",
                "00000001111111111111000000000000",
                "00000000111111111100000000000000",
                "00000000000000000000000000000000",
                "00000000000000000000000000000000",
                "00000000000000000000000000000000",
                "00000000000000000000000000000000",
                "00000000000000000000000000000000",
                "00000000000000000000000000000000",
                "00000000000000000000000000000000",
                "00000000000000000000000000000000",
                "00000000000000000000000000000000"
              ]
            },
            "plane_coordinate_native": -0.000781573,
            "segment_count": 28
          },
          {
            "boundary_samples_normalized": [
              [
                -0.4924849,
                -0.0034281
              ],
              [
                -0.4777881,
                -0.0617081
              ],
              [
                -0.4178859,
                -0.1275527
              ],
              [
                -0.3397712,
                -0.1869152
              ],
              [
                -0.2365404,
                -0.2384829
              ],
              [
                -0.0714194,
                -0.2381053
              ],
              [
                0.0900617,
                -0.226439
              ],
              [
                0.1896239,
                -0.2165197
              ],
              [
                0.429684,
                -0.1064389
              ],
              [
                0.4701432,
                -0.0885971
              ],
              [
                0.4725158,
                -0.0858609
              ],
              [
                0.473044,
                -0.0808891
              ],
              [
                0.462267,
                0.0327686
              ],
              [
                0.3723291,
                0.1225011
              ],
              [
                0.3070591,
                0.1819706
              ],
              [
                0.2233763,
                0.2051032
              ],
              [
                0.06116,
                0.239719
              ],
              [
                0.011597,
                0.2390587
              ],
              [
                -0.1087654,
                0.2253246
              ],
              [
                -0.1776037,
                0.1989193
              ],
              [
                -0.3266324,
                0.1778257
              ],
              [
                -0.3753863,
                0.1609546
              ],
              [
                -0.4087832,
                0.138087
              ],
              [
                -0.4819846,
                0.050694
              ]
            ],
            "bounds_normalized": {
              "dimensions": [
                0.965528882,
                0.478201872
              ],
              "max": [
                0.473043999,
                0.239719014
              ],
              "min": [
                -0.492484883,
                -0.238482858
              ]
            },
            "centroid_normalized": [
              -0.014674343,
              0.012999561
            ],
            "fraction": 0.5,
            "mask": {
              "encoding": "rows_top_to_bottom_1bit_text",
              "occupied_bbox_pixels": [
                2,
                9,
                29,
                22
              ],
              "occupied_fraction": 0.306640625,
              "occupied_pixel_count": 314,
              "origin": "bottom_left",
              "resolution": [
                32,
                32
              ],
              "rows": [
                "00000000000000000000000000000000",
                "00000000000000000000000000000000",
                "00000000000000000000000000000000",
                "00000000000000000000000000000000",
                "00000000000000000000000000000000",
                "00000000000000000000000000000000",
                "00000000000000000000000000000000",
                "00000000000000000000000000000000",
                "00000000000000000000000000000000",
                "00000000000011111111100000000000",
                "00000011111111111111111110000000",
                "00001111111111111111111101000000",
                "00011111111111111111111110100000",
                "00111111111111111111111111010000",
                "00111111111111111111111111101000",
                "00111111111111111111111111110100",
                "00111111111111111111111111111100",
                "00111111111111111111111111111100",
                "00111111111111111111111111111100",
                "00011111111111111111111111110000",
                "00001111111111111111111111000000",
                "00000011111111111111111100000000",
                "00000001111111111111110000000000",
                "00000000000000000000000000000000",
                "00000000000000000000000000000000",
                "00000000000000000000000000000000",
                "00000000000000000000000000000000",
                "00000000000000000000000000000000",
                "00000000000000000000000000000000",
                "00000000000000000000000000000000",
                "00000000000000000000000000000000",
                "00000000000000000000000000000000"
              ]
            },
            "plane_coordinate_native": 0.000105736,
            "segment_count": 24
          },
          {
            "boundary_samples_normalized": [
              [
                -0.4039228,
                0.0252174
              ],
              [
                -0.388235,
                -0.0314789
              ],
              [
                -0.364387,
                -0.0671596
              ],
              [
                -0.3507554,
                -0.081544
              ],
              [
                -0.1527293,
                -0.1682694
              ],
              [
                0.103806,
                -0.1451465
              ],
              [
                0.1673171,
                -0.1428826
              ],
              [
                0.2418881,
                -0.1003166
              ],
              [
                0.299781,
                -0.0539169
              ],
              [
                0.3185133,
                0.0005315
              ],
              [
                0.3362455,
                0.0569692
              ],
              [
                0.2777466,
                0.1094579
              ],
              [
                0.2056169,
                0.1678763
              ],
              [
                0.1248318,
                0.1957129
              ],
              [
                -0.03489,
                0.1991446
              ],
              [
                -0.0793776,
                0.2004844
              ],
              [
                -0.2911772,
                0.1278321
              ],
              [
                -0.3111252,
                0.1186304
              ],
              [
                -0.3477101,
                0.0946365
              ],
              [
                -0.4011778,
                0.0496375
              ]
            ],
            "bounds_normalized": {
              "dimensions": [
                0.740168303,
                0.368753851
              ],
              "max": [
                0.336245513,
                0.200484419
              ],
              "min": [
                -0.40392279,
                -0.168269432
              ]
            },
            "centroid_normalized": [
              -0.05248705,
              0.027770814
            ],
            "fraction": 0.75,
            "mask": {
              "encoding": "rows_top_to_bottom_1bit_text",
              "occupied_bbox_pixels": [
                4,
                11,
                25,
                21
              ],
              "occupied_fraction": 0.186523438,
              "occupied_pixel_count": 191,
              "origin": "bottom_left",
              "resolution": [
                32,
                32
              ],
              "rows": [
                "00000000000000000000000000000000",
                "00000000000000000000000000000000",
                "00000000000000000000000000000000",
                "00000000000000000000000000000000",
                "00000000000000000000000000000000",
                "00000000000000000000000000000000",
                "00000000000000000000000000000000",
                "00000000000000000000000000000000",
                "00000000000000000000000000000000",
                "00000000000000000000000000000000",
                "00000000000011111111100000000000",
                "00000000011111111111111000000000",
                "00000011111111111111111100000000",
                "00000111111111111111111010000000",
                "00001111111111111111111111000000",
                "00001111111111111111111111000000",
                "00001111111111111111111110000000",
                "00000111111111111111111110000000",
                "00000111111111111111111100000000",
                "00000001111111111111111000000000",
                "00000000001111111111100000000000",
                "00000000000000000000000000000000",
                "00000000000000000000000000000000",
                "00000000000000000000000000000000",
                "00000000000000000000000000000000",
                "00000000000000000000000000000000",
                "00000000000000000000000000000000",
                "00000000000000000000000000000000",
                "00000000000000000000000000000000",
                "00000000000000000000000000000000",
                "00000000000000000000000000000000",
                "00000000000000000000000000000000"
              ]
            },
            "plane_coordinate_native": 0.000993045,
            "segment_count": 20
          },
          {
            "boundary_samples_normalized": [
              [
                -0.2262351,
                0.016487
              ],
              [
                -0.1454933,
                -0.0687135
              ],
              [
                -0.0756156,
                -0.0993163
              ],
              [
                0.0149082,
                -0.0911569
              ],
              [
                0.0782436,
                -0.0888993
              ],
              [
                0.1512189,
                -0.0677676
              ],
              [
                0.1935487,
                -0.0338414
              ],
              [
                0.2238696,
                0.0542911
              ],
              [
                0.227319,
                0.0652699
              ],
              [
                0.1714786,
                0.1153733
              ],
              [
                -0.0178338,
                0.1590818
              ],
              [
                -0.052078,
                0.1601131
              ],
              [
                -0.062209,
                0.1566379
              ],
              [
                -0.2049304,
                0.090803
              ],
              [
                -0.2542756,
                0.0584404
              ]
            ],
            "bounds_normalized": {
              "dimensions": [
                0.481594661,
                0.259429464
              ],
              "max": [
                0.22731904,
                0.160113115
              ],
              "min": [
                -0.254275621,
                -0.09931635
              ]
            },
            "centroid_normalized": [
              0.001461054,
              0.028453494
            ],
            "fraction": 0.9,
            "mask": {
              "encoding": "rows_top_to_bottom_1bit_text",
              "occupied_bbox_pixels": [
                8,
                13,
                22,
                20
              ],
              "occupied_fraction": 0.084960938,
              "occupied_pixel_count": 87,
              "origin": "bottom_left",
              "resolution": [
                32,
                32
              ],
              "rows": [
                "00000000000000000000000000000000",
                "00000000000000000000000000000000",
                "00000000000000000000000000000000",
                "00000000000000000000000000000000",
                "00000000000000000000000000000000",
                "00000000000000000000000000000000",
                "00000000000000000000000000000000",
                "00000000000000000000000000000000",
                "00000000000000000000000000000000",
                "00000000000000000000000000000000",
                "00000000000000000000000000000000",
                "00000000000001111100000000000000",
                "00000000000111111111100000000000",
                "00000000011111111111110000000000",
                "00000000111111111111111000000000",
                "00000000011111111111111000000000",
                "00000000001111111111110000000000",
                "00000000000111111111100000000000",
                "00000000000011111111000000000000",
                "00000000000000000000000000000000",
                "00000000000000000000000000000000",
                "00000000000000000000000000000000",
                "00000000000000000000000000000000",
                "00000000000000000000000000000000",
                "00000000000000000000000000000000",
                "00000000000000000000000000000000",
                "00000000000000000000000000000000",
                "00000000000000000000000000000000",
                "00000000000000000000000000000000",
                "00000000000000000000000000000000",
                "00000000000000000000000000000000",
                "00000000000000000000000000000000"
              ]
            },
            "plane_coordinate_native": 0.00152543,
            "segment_count": 15
          }
        ]
      }
    },
    "normalization": {
      "method": "uniform_scale_about_oriented_bounds_center",
      "normalized_extent": "largest dimension equals 1.0; aspect ratio is preserved",
      "oriented_bounds_center": [
        0.000114636,
        -3.3594e-05,
        0.000105736
      ],
      "pca_basis_world": [
        [
          -0.048903945,
          0.268826916,
          0.961946201
        ],
        [
          -0.20461222,
          0.939976593,
          -0.273089445
        ],
        [
          -0.977620705,
          -0.210181099,
          0.009036708
        ]
      ],
      "pca_origin_world": [
        -0.007025516,
        0.779285607,
        -0.077032027
      ],
      "uniform_scale_native": 0.007631009
    },
    "silhouettes": {
      "pca_axis_aligned": {
        "xy": {
          "encoding": "rows_top_to_bottom_1bit_text",
          "occupied_bbox_pixels": [
            2,
            13,
            45,
            34
          ],
          "occupied_fraction": 0.326388889,
          "occupied_pixel_count": 752,
          "origin": "bottom_left",
          "resolution": [
            48,
            48
          ],
          "rows": [
            "000000000000000000000000000000000000000000000000",
            "000000000000000000000000000000000000000000000000",
            "000000000000000000000000000000000000000000000000",
            "000000000000000000000000000000000000000000000000",
            "000000000000000000000000000000000000000000000000",
            "000000000000000000000000000000000000000000000000",
            "000000000000000000000000000000000000000000000000",
            "000000000000000000000000000000000000000000000000",
            "000000000000000000000000000000000000000000000000",
            "000000000000000000000000000000000000000000000000",
            "000000000000000000000000000000000000000000000000",
            "000000000000000000000000000000000000000000000000",
            "000000000000000000000000000000000000000000000000",
            "000000000000000001111111111110000000000000000000",
            "000000000000001111111111111111111100000000000000",
            "000000000000111111111111111111111111100000000000",
            "000000011111111111111111111111111111111000000000",
            "000000111111111111111111111111111111111000000000",
            "000001111111111111111111111111111111111110000000",
            "000011111111111111111111111111111111111111000000",
            "000011111111111111111111111111111111111111100000",
            "000111111111111111111111111111111111111111110000",
            "001111111111111111111111111111111111111111111000",
            "001111111111111111111111111111111111111111111100",
            "001111111111111111111111111111111111111111111100",
            "000111111111111111111111111111111111111111111100",
            "000111111111111111111111111111111111111111111100",
            "000111111111111111111111111111111111111111111100",
            "000011111111111111111111111111111111111111111000",
            "000001111111111111111111111111111111111111110000",
            "000000111111111111111111111111111111111111000000",
            "000000001111111111111111111111111111111100000000",
            "000000000111111111111111111111111111000000000000",
            "000000000011111111111111111111111100000000000000",
            "000000000000111111111111111110000000000000000000",
            "000000000000000000000000000000000000000000000000",
            "000000000000000000000000000000000000000000000000",
            "000000000000000000000000000000000000000000000000",
            "000000000000000000000000000000000000000000000000",
            "000000000000000000000000000000000000000000000000",
            "000000000000000000000000000000000000000000000000",
            "000000000000000000000000000000000000000000000000",
            "000000000000000000000000000000000000000000000000",
            "000000000000000000000000000000000000000000000000",
            "000000000000000000000000000000000000000000000000",
            "000000000000000000000000000000000000000000000000",
            "000000000000000000000000000000000000000000000000",
            "000000000000000000000000000000000000000000000000"
          ]
        },
        "xz": {
          "encoding": "rows_top_to_bottom_1bit_text",
          "occupied_bbox_pixels": [
            2,
            14,
            45,
            33
          ],
          "occupied_fraction": 0.289930556,
          "occupied_pixel_count": 668,
          "origin": "bottom_left",
          "resolution": [
            48,
            48
          ],
          "rows": [
            "000000000000000000000000000000000000000000000000",
            "000000000000000000000000000000000000000000000000",
            "000000000000000000000000000000000000000000000000",
            "000000000000000000000000000000000000000000000000",
            "000000000000000000000000000000000000000000000000",
            "000000000000000000000000000000000000000000000000",
            "000000000000000000000000000000000000000000000000",
            "000000000000000000000000000000000000000000000000",
            "000000000000000000000000000000000000000000000000",
            "000000000000000000000000000000000000000000000000",
            "000000000000000000000000000000000000000000000000",
            "000000000000000000000000000000000000000000000000",
            "000000000000000000000000000000000000000000000000",
            "000000000000000000000000000000000000000000000000",
            "000000000000000011111111111111100000000000000000",
            "000000000000011111111111111111111100000000000000",
            "000000000011111111111111111111111111000000000000",
            "000000001111111111111111111111111111100000000000",
            "000000011111111111111111111111111111110000000000",
            "000001111111111111111111111111111111111100000000",
            "000001111111111111111111111111111111111110000000",
            "000111111111111111111111111111111111111111100000",
            "000111111111111111111111111111111111111111110000",
            "000111111111111111111111111111111111111111111000",
            "001111111111111111111111111111111111111111111000",
            "001111111111111111111111111111111111111111111000",
            "001111111111111111111111111111111111111111111100",
            "000111111111111111111111111111111111111111111100",
            "000011111111111111111111111111111111111111111000",
            "000001111111111111111111111111111111111111100000",
            "000000111111111111111111111111111111111111000000",
            "000000011111111111111111111111111111111100000000",
            "000000000011111111111111111111000000000000000000",
            "000000000000000011111111111000000000000000000000",
            "000000000000000000000000000000000000000000000000",
            "000000000000000000000000000000000000000000000000",
            "000000000000000000000000000000000000000000000000",
            "000000000000000000000000000000000000000000000000",
            "000000000000000000000000000000000000000000000000",
            "000000000000000000000000000000000000000000000000",
            "000000000000000000000000000000000000000000000000",
            "000000000000000000000000000000000000000000000000",
            "000000000000000000000000000000000000000000000000",
            "000000000000000000000000000000000000000000000000",
            "000000000000000000000000000000000000000000000000",
            "000000000000000000000000000000000000000000000000",
            "000000000000000000000000000000000000000000000000",
            "000000000000000000000000000000000000000000000000"
          ]
        },
        "yz": {
          "encoding": "rows_top_to_bottom_1bit_text",
          "occupied_bbox_pixels": [
            13,
            14,
            34,
            33
          ],
          "occupied_fraction": 0.154947917,
          "occupied_pixel_count": 357,
          "origin": "bottom_left",
          "resolution": [
            48,
            48
          ],
          "rows": [
            "000000000000000000000000000000000000000000000000",
            "000000000000000000000000000000000000000000000000",
            "000000000000000000000000000000000000000000000000",
            "000000000000000000000000000000000000000000000000",
            "000000000000000000000000000000000000000000000000",
            "000000000000000000000000000000000000000000000000",
            "000000000000000000000000000000000000000000000000",
            "000000000000000000000000000000000000000000000000",
            "000000000000000000000000000000000000000000000000",
            "000000000000000000000000000000000000000000000000",
            "000000000000000000000000000000000000000000000000",
            "000000000000000000000000000000000000000000000000",
            "000000000000000000000000000000000000000000000000",
            "000000000000000000000000000000000000000000000000",
            "000000000000000000000111111110000000000000000000",
            "000000000000000000001111111111100000000000000000",
            "000000000000000000011111111111110000000000000000",
            "000000000000000000111111111111110000000000000000",
            "000000000000000011111111111111111000000000000000",
            "000000000000000011111111111111111000000000000000",
            "000000000000001111111111111111111100000000000000",
            "000000000000001111111111111111111100000000000000",
            "000000000000001111111111111111111100000000000000",
            "000000000000011111111111111111111110000000000000",
            "000000000000011111111111111111111110000000000000",
            "000000000000011111111111111111111110000000000000",
            "000000000000011111111111111111111110000000000000",
            "000000000000011111111111111111111110000000000000",
            "000000000000011111111111111111111110000000000000",
            "000000000000011111111111111111111110000000000000",
            "000000000000001111111111111111111110000000000000",
            "000000000000000011111111111111111100000000000000",
            "000000000000000000011111111111111100000000000000",
            "000000000000000000000000111111111000000000000000",
            "000000000000000000000000000000000000000000000000",
            "000000000000000000000000000000000000000000000000",
            "000000000000000000000000000000000000000000000000",
            "000000000000000000000000000000000000000000000000",
            "000000000000000000000000000000000000000000000000",
            "000000000000000000000000000000000000000000000000",
            "000000000000000000000000000000000000000000000000",
            "000000000000000000000000000000000000000000000000",
            "000000000000000000000000000000000000000000000000",
            "000000000000000000000000000000000000000000000000",
            "000000000000000000000000000000000000000000000000",
            "000000000000000000000000000000000000000000000000",
            "000000000000000000000000000000000000000000000000",
            "000000000000000000000000000000000000000000000000"
          ]
        }
      },
      "world_axis_aligned": {
        "xy": {
          "encoding": "rows_top_to_bottom_1bit_text",
          "occupied_bbox_pixels": [
            14,
            11,
            33,
            36
          ],
          "occupied_fraction": 0.176649306,
          "occupied_pixel_count": 407,
          "origin": "bottom_left",
          "resolution": [
            48,
            48
          ],
          "rows": [
            "000000000000000000000000000000000000000000000000",
            "000000000000000000000000000000000000000000000000",
            "000000000000000000000000000000000000000000000000",
            "000000000000000000000000000000000000000000000000",
            "000000000000000000000000000000000000000000000000",
            "000000000000000000000000000000000000000000000000",
            "000000000000000000000000000000000000000000000000",
            "000000000000000000000000000000000000000000000000",
            "000000000000000000000000000000000000000000000000",
            "000000000000000000000000000000000000000000000000",
            "000000000000000000000000000000000000000000000000",
            "000000000000000000000000110000000000000000000000",
            "000000000000000000000111111110000000000000000000",
            "000000000000000000011111111111100000000000000000",
            "000000000000000000111111111111110000000000000000",
            "000000000000000001111111111111111000000000000000",
            "000000000000000111111111111111111100000000000000",
            "000000000000000111111111111111111100000000000000",
            "000000000000000111111111111111111100000000000000",
            "000000000000000111111111111111111100000000000000",
            "000000000000000111111111111111111100000000000000",
            "000000000000001111111111111111111100000000000000",
            "000000000000001111111111111111111100000000000000",
            "000000000000001111111111111111111100000000000000",
            "000000000000001111111111111111111100000000000000",
            "000000000000001111111111111111111100000000000000",
            "000000000000001111111111111111111100000000000000",
            "000000000000000111111111111111111100000000000000",
            "000000000000000111111111111111111100000000000000",
            "000000000000000011111111111111111100000000000000",
            "000000000000000001111111111111111100000000000000",
            "000000000000000000111111111111111100000000000000",
            "000000000000000000011111111111111000000000000000",
            "000000000000000000000111111111111000000000000000",
            "000000000000000000000011111111111000000000000000",
            "000000000000000000000001111111110000000000000000",
            "000000000000000000000000011111000000000000000000",
            "000000000000000000000000000000000000000000000000",
            "000000000000000000000000000000000000000000000000",
            "000000000000000000000000000000000000000000000000",
            "000000000000000000000000000000000000000000000000",
            "000000000000000000000000000000000000000000000000",
            "000000000000000000000000000000000000000000000000",
            "000000000000000000000000000000000000000000000000",
            "000000000000000000000000000000000000000000000000",
            "000000000000000000000000000000000000000000000000",
            "000000000000000000000000000000000000000000000000",
            "000000000000000000000000000000000000000000000000"
          ]
        },
        "xz": {
          "encoding": "rows_top_to_bottom_1bit_text",
          "occupied_bbox_pixels": [
            14,
            2,
            33,
            45
          ],
          "occupied_fraction": 0.290364583,
          "occupied_pixel_count": 669,
          "origin": "bottom_left",
          "resolution": [
            48,
            48
          ],
          "rows": [
            "000000000000000000000000000000000000000000000000",
            "000000000000000000000000000000000000000000000000",
            "000000000000000000000000001100000000000000000000",
            "000000000000000000000000111110000000000000000000",
            "000000000000000000000001111111000000000000000000",
            "000000000000000000000111111111100000000000000000",
            "000000000000000000001111111111100000000000000000",
            "000000000000000000001111111111100000000000000000",
            "000000000000000000011111111111110000000000000000",
            "000000000000000000011111111111110000000000000000",
            "000000000000000000111111111111110000000000000000",
            "000000000000000000111111111111110000000000000000",
            "000000000000000001111111111111110000000000000000",
            "000000000000000011111111111111110000000000000000",
            "000000000000000011111111111111110000000000000000",
            "000000000000000111111111111111110000000000000000",
            "000000000000000111111111111111110000000000000000",
            "000000000000000111111111111111111000000000000000",
            "000000000000000111111111111111111000000000000000",
            "000000000000001111111111111111111100000000000000",
            "000000000000001111111111111111111100000000000000",
            "000000000000001111111111111111111100000000000000",
            "000000000000001111111111111111111100000000000000",
            "000000000000001111111111111111111100000000000000",
            "000000000000001111111111111111111100000000000000",
            "000000000000001111111111111111111100000000000000",
            "000000000000001111111111111111111100000000000000",
            "000000000000001111111111111111111100000000000000",
            "000000000000001111111111111111111100000000000000",
            "000000000000001111111111111111111100000000000000",
            "000000000000001111111111111111111100000000000000",
            "000000000000001111111111111111111100000000000000",
            "000000000000000111111111111111111100000000000000",
            "000000000000000111111111111111111100000000000000",
            "000000000000000011111111111111111100000000000000",
            "000000000000000011111111111111111000000000000000",
            "000000000000000001111111111111111000000000000000",
            "000000000000000001111111111111111000000000000000",
            "000000000000000000111111111111111000000000000000",
            "000000000000000000111111111111111000000000000000",
            "000000000000000000011111111111111000000000000000",
            "000000000000000000011111111111111000000000000000",
            "000000000000000000001111111111100000000000000000",
            "000000000000000000000111111111000000000000000000",
            "000000000000000000000011111110000000000000000000",
            "000000000000000000000000001100000000000000000000",
            "000000000000000000000000000000000000000000000000",
            "000000000000000000000000000000000000000000000000"
          ]
        },
        "yz": {
          "encoding": "rows_top_to_bottom_1bit_text",
          "occupied_bbox_pixels": [
            11,
            2,
            36,
            45
          ],
          "occupied_fraction": 0.33203125,
          "occupied_pixel_count": 765,
          "origin": "bottom_left",
          "resolution": [
            48,
            48
          ],
          "rows": [
            "000000000000000000000000000000000000000000000000",
            "000000000000000000000000000000000000000000000000",
            "000000000000000000000000000110000000000000000000",
            "000000000000000000000000011111110000000000000000",
            "000000000000000000000000111111110000000000000000",
            "000000000000000000000001111111111000000000000000",
            "000000000000000000000011111111111000000000000000",
            "000000000000000000000111111111111100000000000000",
            "000000000000000000000111111111111100000000000000",
            "000000000000000000001111111111111110000000000000",
            "000000000000000000011111111111111110000000000000",
            "000000000000000000011111111111111111000000000000",
            "000000000000000000111111111111111111000000000000",
            "000000000000000001111111111111111111100000000000",
            "000000000000000001111111111111111111100000000000",
            "000000000000000011111111111111111111100000000000",
            "000000000000000011111111111111111111100000000000",
            "000000000000000011111111111111111111000000000000",
            "000000000000000111111111111111111111000000000000",
            "000000000000000111111111111111111111000000000000",
            "000000000000001111111111111111111111000000000000",
            "000000000000001111111111111111111111000000000000",
            "000000000000001111111111111111111111000000000000",
            "000000000000001111111111111111111111000000000000",
            "000000000000011111111111111111111111000000000000",
            "000000000000011111111111111111111111000000000000",
            "000000000000011111111111111111111111000000000000",
            "000000000000111111111111111111111110000000000000",
            "000000000000111111111111111111111110000000000000",
            "000000000000111111111111111111111110000000000000",
            "000000000000111111111111111111111110000000000000",
            "000000000001111111111111111111111110000000000000",
            "000000000001111111111111111111111100000000000000",
            "000000000000111111111111111111111100000000000000",
            "000000000000111111111111111111111000000000000000",
            "000000000000111111111111111111110000000000000000",
            "000000000000111111111111111111110000000000000000",
            "000000000000011111111111111111100000000000000000",
            "000000000000011111111111111111000000000000000000",
            "000000000000011111111111111110000000000000000000",
            "000000000000001111111111111110000000000000000000",
            "000000000000001111111111111100000000000000000000",
            "000000000000000111111111111000000000000000000000",
            "000000000000000011111111110000000000000000000000",
            "000000000000000001111111000000000000000000000000",
            "000000000000000000011100000000000000000000000000",
            "000000000000000000000000000000000000000000000000",
            "000000000000000000000000000000000000000000000000"
          ]
        }
      }
    }
  },
  "schema_version": "1.0.0",
  "source": {
    "aggregate": false,
    "filename": "united-female-v1.5.glb",
    "format": "glb",
    "logical_mesh_index": 110,
    "logical_mesh_name": "Allen_pineal_body_L",
    "path": "/Users/eimis/Documents/HACKTHONS-2025/ServerPodHackathon/3D world/reference-atlas/models/hra/united-female-v1.5.glb",
    "sha256": "472567a56896b9b7890508da6501fbf858e56aaa30745365f7a71ade782b529c"
  },
  "surface_area": 7.1134e-05,
  "topology": {
    "boundary_edge_count": 0,
    "connected_component_count": 1,
    "inconsistently_wound_edge_count": 0,
    "is_edge_manifold": true,
    "is_watertight": true,
    "is_winding_consistent": true,
    "nonmanifold_edge_count": 0,
    "unique_edge_count": 147
  },
  "units": {
    "native": "source_units_unspecified",
    "note": "All physical measurements preserve source units; area and volume use squared/cubed source units."
  },
  "volume_if_watertight": 4.6e-08,
  "volume_orientation_repaired_in_memory": true
}
